stock_catcher/__init__.py
stock_catcher/__main__.py
stock_catcher/catcher.py
stock_catcher/config.toml
stock_catcher/data/CAC40_2024.csv
stock_catcher-1.0.0.dist-info/LICENSE
stock_catcher-1.0.0.dist-info/METADATA
stock_catcher-1.0.0.dist-info/WHEEL
stock_catcher-1.0.0.dist-info/entry_points.txt
stock_catcher-1.0.0.dist-info/top_level.txt
stock_catcher-1.0.0.dist-info/RECORD
