Metadata-Version: 2.2
Name: stock_catcher
Version: 1.0.0
Summary: Read the latest stock news
Author-email: Pengfei <liu.pengfei@hotmail.fr>
License:                                  Apache License
Project-URL: repository, https://github.com/pengfei99/py-packaging
Project-URL: documentation, https://github.com/pengfei99/py-packaging/blob/main/docs/packaging_python_scripts.md
Keywords: cac40,stock,finance
Classifier: License :: OSI Approved :: MIT License
Classifier: Programming Language :: Python
Classifier: Programming Language :: Python :: 3
Requires-Python: >=3.9
License-File: LICENSE
Requires-Dist: pandas
Requires-Dist: yfinance
Requires-Dist: tomli; python_version < "3.13"
Provides-Extra: build
Requires-Dist: build; extra == "build"
Requires-Dist: twine; extra == "build"
Provides-Extra: dev
Requires-Dist: black; extra == "dev"
Requires-Dist: bumpver; extra == "dev"
Requires-Dist: isort; extra == "dev"
Requires-Dist: mypy; extra == "dev"
Requires-Dist: pytest; extra == "dev"
